Metadata-Version: 2.1
Name: torchapply
Version: 0.0.4
Summary: Apply a torch model to a single or multiple datapoints.
Home-page: https://github.com/blythed/torchapply
Author: Duncan Blythe
Author-email: firstnamelastname@gmail.com
License: MIT License
Classifier: Programming Language :: Python :: 3.7
Classifier: Programming Language :: Python :: 3.8
Classifier: Programming Language :: Python :: 3.9
Classifier: Topic :: Scientific/Engineering
Classifier: Topic :: Scientific/Engineering :: Artificial Intelligence
Requires-Python: >=3.7
License-File: LICENSE
